guardzhanzhan/__init__.py
guardzhanzhan/guardzhanzhan.py
guardzhanzhan-0.0.1.dist-info/LICENSE
guardzhanzhan-0.0.1.dist-info/METADATA
guardzhanzhan-0.0.1.dist-info/WHEEL
guardzhanzhan-0.0.1.dist-info/top_level.txt
guardzhanzhan-0.0.1.dist-info/RECORD
