Metadata-Version: 2.1
Name: guardzhanzhan
Version: 0.0.1
Summary: szhanzhan
Home-page: https://github.com/BigDataFounder/guardzhanzhan
Author: hurpe
Author-email: 1017720714@qq.com
License: MIT
Platform: UNKNOWN
